keeya/__init__.py
keeya/keeya.py
keeya-1.0.5.dist-info/licenses/LICENSE
keeya-1.0.5.dist-info/METADATA
keeya-1.0.5.dist-info/WHEEL
keeya-1.0.5.dist-info/entry_points.txt
keeya-1.0.5.dist-info/top_level.txt
keeya-1.0.5.dist-info/RECORD
