Metadata-Version: 2.4
Name: keeya
Version: 1.0.5
Summary: keeya.py - AI-Powered Python Code Generation
Author-email: Jay Kilaparthi <jayakeerthk@gmail.com>
License: MIT
Project-URL: Homepage, https://github.com/jayyvk/keeya-py
Project-URL: Repository, https://github.com/jayyvk/keeya-py.git
Project-URL: Issues, https://github.com/jayyvk/keeya-py/issues
Keywords: ai,code-generation,python,automation,gemini
Classifier: Development Status :: 4 - Beta
Classifier: Intended Audience :: Developers
Classifier: License :: OSI Approved :: MIT License
Classifier: Operating System :: OS Independent
Classifier: Programming Language :: Python :: 3
Classifier: Programming Language :: Python :: 3.8
Classifier: Programming Language :: Python :: 3.9
Classifier: Programming Language :: Python :: 3.10
Classifier: Programming Language :: Python :: 3.11
Classifier: Programming Language :: Python :: 3.12
Classifier: Topic :: Software Development :: Code Generators
Classifier: Topic :: Scientific/Engineering :: Artificial Intelligence
Requires-Python: >=3.8
License-File: LICENSE
Requires-Dist: requests>=2.25.0
Requires-Dist: pandas>=1.3.0
Requires-Dist: numpy>=1.21.0
Requires-Dist: matplotlib>=3.5.0
Requires-Dist: seaborn>=0.11.0
Requires-Dist: scikit-learn>=1.0.0
Dynamic: license-file
